shibudb_client.py
shibudb_client-1.0.4.dist-info/LICENSE
shibudb_client-1.0.4.dist-info/METADATA
shibudb_client-1.0.4.dist-info/WHEEL
shibudb_client-1.0.4.dist-info/entry_points.txt
shibudb_client-1.0.4.dist-info/top_level.txt
shibudb_client-1.0.4.dist-info/RECORD
