Metadata-Version: 2.1
Name: shibudb-client
Version: 1.0.4
Summary: A comprehensive Python client for ShibuDb database
Home-page: https://github.com/Podcopic-Labs/ShibuDb
Author: ShibuDb Team
Author-email: support@shibudb.com
Project-URL: Bug Reports, https://github.com/Podcopic-Labs/ShibuDb/issues
Project-URL: Source, https://github.com/Podcopic-Labs/ShibuDb
Project-URL: Documentation, https://github.com/Podcopic-Labs/ShibuDb/tree/main/python_client
Keywords: database,key-value,vector,similarity-search,embedded
Classifier: Development Status :: 4 - Beta
Classifier: Intended Audience :: Developers
Classifier: License :: OSI Approved :: MIT License
Classifier: Operating System :: OS Independent
Classifier: Programming Language :: Python :: 3
Classifier: Programming Language :: Python :: 3.7
Classifier: Programming Language :: Python :: 3.8
Classifier: Programming Language :: Python :: 3.9
Classifier: Programming Language :: Python :: 3.10
Classifier: Programming Language :: Python :: 3.11
Classifier: Topic :: Database
Classifier: Topic :: Software Development :: Libraries :: Python Modules
Requires-Python: >=3.7
License-File: LICENSE
Provides-Extra: dev
Requires-Dist: pytest >=6.0 ; extra == 'dev'
Requires-Dist: pytest-cov >=2.0 ; extra == 'dev'
Requires-Dist: black >=21.0 ; extra == 'dev'
Requires-Dist: flake8 >=3.8 ; extra == 'dev'
Requires-Dist: mypy >=0.800 ; extra == 'dev'
